ecometpy-1.0.0-py3.9-nspkg.pth
ecometpy/version.py
ecometpy/tools/__init__.py
ecometpy/tools/h4toh5.py
ecometpy/tools/hdf4pro.py
ecometpy/tools/hdfpro.py
ecometpy/tools/jsonpro.py
ecometpy/tools/nc2tif.py
ecometpy/tools/ncpro.py
ecometpy/tools/tifpro.py
ecometpy-1.0.0.dist-info/LICENSE
ecometpy-1.0.0.dist-info/METADATA
ecometpy-1.0.0.dist-info/WHEEL
ecometpy-1.0.0.dist-info/namespace_packages.txt
ecometpy-1.0.0.dist-info/top_level.txt
ecometpy-1.0.0.dist-info/RECORD
